typing_inspect.py
typing_inspect-0.7.1.dist-info/LICENSE
typing_inspect-0.7.1.dist-info/METADATA
typing_inspect-0.7.1.dist-info/WHEEL
typing_inspect-0.7.1.dist-info/top_level.txt
typing_inspect-0.7.1.dist-info/RECORD
